defpi/Connection.py
defpi/ConnectionHandler.py
defpi/ConnectionHandlerManager.py
defpi/ConnectionManager.py
defpi/DefPiParameters.py
defpi/Exceptions.py
defpi/HandShakeMonitor.py
defpi/HeartBeatMonitor.py
defpi/Service.py
defpi/ServiceExecutor.py
defpi/ServiceMain.py
defpi/ServiceManager.py
defpi/TCPConnection.py
defpi/__init__.py
defpi/common/ProtobufMessageSerializer.py
defpi/common/ScheduledExecutor.py
defpi/common/TCPSocket.py
defpi/common/XSDMessageSerializer.py
defpi/common/__init__.py
defpi/protobufs/Connection_pb2.py
defpi/protobufs/Service_pb2.py
defpi/protobufs/__init__.py
defpi-18.5.7.dist-info/DESCRIPTION.rst
defpi-18.5.7.dist-info/METADATA
defpi-18.5.7.dist-info/RECORD
defpi-18.5.7.dist-info/WHEEL
defpi-18.5.7.dist-info/metadata.json
defpi-18.5.7.dist-info/top_level.txt
