Metadata-Version: 2.0
Name: defpi
Version: 18.5.7
Summary: Python module for dEF-Pi
Home-page: UNKNOWN
Author: Maarten Kollenstart
Author-email: maarten.kollenstart@tno.nl
License: UNKNOWN
Platform: UNKNOWN
Requires-Python: ~=3.5
Requires-Dist: protobuf
Requires-Dist: pyxb
Requires-Dist: requests
